flowmyna/__init__.py
flowmyna/async_client.py
flowmyna/client.py
flowmyna/exceptions.py
flowmyna/py.typed
flowmyna/types.py
flowmyna-0.1.0.dist-info/licenses/LICENSE
flowmyna-0.1.0.dist-info/METADATA
flowmyna-0.1.0.dist-info/WHEEL
flowmyna-0.1.0.dist-info/top_level.txt
flowmyna-0.1.0.dist-info/RECORD
