Metadata-Version: 2.4
Name: flowmyna
Version: 0.1.0
Summary: Official Python SDK for FlowMyna - Process Mining Event Tracking
Author-email: FlowMyna <daniel@flowmyna.com>
License: MIT
Project-URL: Homepage, https://flowmyna.com
Project-URL: Documentation, https://flowmyna.com/api/sdks/python
Project-URL: Repository, https://github.com/flowmyna/flowmyna-python
Project-URL: Changelog, https://github.com/flowmyna/flowmyna-python/blob/main/CHANGELOG.md
Keywords: flowmyna,process-mining,event-tracking,sdk,analytics
Classifier: Development Status :: 4 - Beta
Classifier: Intended Audience :: Developers
Classifier: License :: OSI Approved :: MIT License
Classifier: Programming Language :: Python :: 3
Classifier: Programming Language :: Python :: 3.8
Classifier: Programming Language :: Python :: 3.9
Classifier: Programming Language :: Python :: 3.10
Classifier: Programming Language :: Python :: 3.11
Classifier: Programming Language :: Python :: 3.12
Classifier: Topic :: Software Development :: Libraries :: Python Modules
Classifier: Typing :: Typed
Requires-Python: >=3.8
License-File: LICENSE
Requires-Dist: httpx>=0.27.0
Provides-Extra: async
Requires-Dist: httpx[http2]>=0.27.0; extra == "async"
Provides-Extra: test
Requires-Dist: pytest>=7.0.0; extra == "test"
Requires-Dist: pytest-cov>=4.0.0; extra == "test"
Requires-Dist: pytest-asyncio>=0.21.0; extra == "test"
Requires-Dist: respx>=0.20.0; extra == "test"
Provides-Extra: dev
Requires-Dist: ruff>=0.4.2; extra == "dev"
Requires-Dist: mypy>=1.0.0; extra == "dev"
Dynamic: license-file
